MANIFEST.in
README.txt
setup.py
docs/HISTORY.txt
docs/LICENSE.txt
src/silva/__init__.py
src/silva.export.html.egg-info/PKG-INFO
src/silva.export.html.egg-info/SOURCES.txt
src/silva.export.html.egg-info/dependency_links.txt
src/silva.export.html.egg-info/namespace_packages.txt
src/silva.export.html.egg-info/not-zip-safe
src/silva.export.html.egg-info/requires.txt
src/silva.export.html.egg-info/top_level.txt
src/silva/export/__init__.py
src/silva/export/html/__init__.py
src/silva/export/html/configure.zcml
src/silva/export/html/html.py
src/silva/export/html/interfaces.py
src/silva/export/html/url.py