Metadata-Version: 1.1
Name: silva.export.html
Version: 3.0
Summary: Export Silva content to standalone HTML
Home-page: https://github.com/silvacms/silva.export.html
Author: Infrae
Author-email: info@infrae.com
License: BSD
Keywords: silva export html
Platform: UNKNOWN
Classifier: Framework :: Zope2
Classifier: License :: OSI Approved :: BSD License
Classifier: Programming Language :: Python
Classifier: Topic :: Software Development :: Libraries :: Python Modules
